Scrapy025Wendang/README.md
Scrapy025Wendang/__init__.py
Scrapy025Wendang/__main__.py
Scrapy025Wendang/file.epub
Scrapy025Wendang/index.html
Scrapy025Wendang/css/__init__.py
Scrapy025Wendang/css/annotations.css
Scrapy025Wendang/css/main.css
Scrapy025Wendang/css/normalize.css
Scrapy025Wendang/css/popup.css
Scrapy025Wendang/font/__init__.py
Scrapy025Wendang/font/fontello.eot
Scrapy025Wendang/font/fontello.svg
Scrapy025Wendang/font/fontello.ttf
Scrapy025Wendang/font/fontello.woff
Scrapy025Wendang/img/__init__.py
Scrapy025Wendang/img/annotator-glyph-sprite.png
Scrapy025Wendang/img/annotator-icon-sprite.png
Scrapy025Wendang/img/apple-touch-icon.png
Scrapy025Wendang/img/cancelfullscreen.png
Scrapy025Wendang/img/close.png
Scrapy025Wendang/img/fullscreen.png
Scrapy025Wendang/img/loader.gif
Scrapy025Wendang/img/menu-icon.png
Scrapy025Wendang/img/save.png
Scrapy025Wendang/img/saved.png
Scrapy025Wendang/img/settings-s.png
Scrapy025Wendang/img/settings.png
Scrapy025Wendang/img/star.png
Scrapy025Wendang/js/__init__.py
Scrapy025Wendang/js/epub.js
Scrapy025Wendang/js/epub.min.js
Scrapy025Wendang/js/epub.min.map
Scrapy025Wendang/js/hooks.min.js
Scrapy025Wendang/js/hooks.min.map
Scrapy025Wendang/js/reader.js
Scrapy025Wendang/js/reader.js.map
Scrapy025Wendang/js/reader.min.js
Scrapy025Wendang/js/reader.min.map
Scrapy025Wendang/js/hooks/__init__.py
Scrapy025Wendang/js/hooks/extensions/__init__.py
Scrapy025Wendang/js/hooks/extensions/highlight.js
Scrapy025Wendang/js/libs/__init__.py
Scrapy025Wendang/js/libs/jquery.min.js
Scrapy025Wendang/js/libs/localforage.min.js
Scrapy025Wendang/js/libs/screenfull.js
Scrapy025Wendang/js/libs/screenfull.min.js
Scrapy025Wendang/js/libs/zip.min.js
Scrapy025Wendang/js/plugins/__init__.py
Scrapy025Wendang/js/plugins/hypothesis.js
Scrapy025Wendang/js/plugins/search.js
scrapy_0_25_wendang-2024.3.1.0.dist-info/METADATA
scrapy_0_25_wendang-2024.3.1.0.dist-info/WHEEL
scrapy_0_25_wendang-2024.3.1.0.dist-info/entry_points.txt
scrapy_0_25_wendang-2024.3.1.0.dist-info/top_level.txt
scrapy_0_25_wendang-2024.3.1.0.dist-info/RECORD
